cursofiap/__init__.py
cursofiap/core.py
cursofiap_package_charleskulkauski-1.0.0.dist-info/METADATA
cursofiap_package_charleskulkauski-1.0.0.dist-info/WHEEL
cursofiap_package_charleskulkauski-1.0.0.dist-info/top_level.txt
cursofiap_package_charleskulkauski-1.0.0.dist-info/RECORD
