Metadata-Version: 2.4
Name: cursofiap-package-charleskulkauski
Version: 1.0.0
Summary: Descricao da sua lib cursofiap
Home-page: https://github.com/charleskulkauski/cursofiap
Author: Charles Kulkauski
Author-email: charleskulkauski@gmail.com
License: MIT
Dynamic: author
Dynamic: author-email
Dynamic: description
Dynamic: description-content-type
Dynamic: home-page
Dynamic: license
Dynamic: summary
